easyPythonpi/__init__.py
easyPythonpi/__main__.py
easyPythonpi/easyPythonpi.py
easyPythonpi/methods/Graph.py
easyPythonpi/methods/__init__.py
easyPythonpi/methods/array.py
easyPythonpi/methods/basics.py
easyPythonpi/methods/bitwiseops.py
easyPythonpi/methods/linkedlist.py
easyPythonpi/methods/matrix.py
easyPythonpi/methods/patternprinting.py
easyPythonpi/methods/search.py
easyPythonpi/methods/shape.py
easyPythonpi/methods/sorting.py
easyPythonpi/methods/statistics.py
easyPythonpi/methods/stringmainpulation.py
easyPythonpi/test/__init__.py
easyPythonpi/test/__main__.py
easyPythonpi/test/test_Bin2Hex.py
easyPythonpi/test/test_FibRefactored.py
easyPythonpi/test/test_basics.py
easyPythonpi/test/test_graph.py
easyPythonpi/test/test_patternprinting.py
easyPythonpi/test/test_search.py
easyPythonpi/test/test_shape.py
easyPythonpi/test/test_statistics.py
easyPythonpi/test/test_stringmanipulation.py
easyPythonpi-1.2.3.dist-info/METADATA
easyPythonpi-1.2.3.dist-info/WHEEL
easyPythonpi-1.2.3.dist-info/top_level.txt
easyPythonpi-1.2.3.dist-info/RECORD
