Metadata-Version: 2.1
Name: easyPythonpi
Version: 1.2.3
Summary: A simple library for Python beginners
Author: extinctsion (Aditya Sharma)
Author-email: <extinctsion@protonmail.com>
Keywords: python,sorting,beginners,sockets
Classifier: Development Status :: 1 - Planning
Classifier: Programming Language :: Python :: 3
Classifier: Operating System :: Unix
Classifier: Operating System :: MacOS :: MacOS X
Classifier: Operating System :: Microsoft :: Windows
Requires-Dist: numpy >=1.19.5
